{
  "uuid": "_a-0000eecf-ec56-8000-9ce5-011c48011c48_186838",
  "name": "AIA_Test_GetLatestExtractionInstanceWithValidation",
  "type": "Expression Rule",
  "description": "Get the latest extraction instance with at least 1 validation",
  "sail_code": "rule!AIA_Extraction_GetInstanceById(\n  identifier: #\"SYSTEM_SYSRULES_queryRecordType_v3\"(\n    recordType: recordType!AIA Extraction Instance,\n    filters: #\"SYSTEM_SYSRULES_queryFilter\"(\n      field: recordType!AIA Extraction Instance.validations,\n      operator: \"not null\"\n    ),\n    pagingInfo: #\"SYSTEM_SYSRULES_pagingInfo\"(\n      startIndex: 1,\n      batchSize: 1,\n      sort: {\n        #\"SYSTEM_SYSRULES_sortInfo\"(\n          field: recordType!AIA Extraction Instance.id\n        )\n      }\n    )\n  ).data[recordType!AIA Extraction Instance.id],\n  additionalFields: {\n    recordType!AIA Extraction Instance.modelVersion.extractionModel.key,\n    recordType!AIA Extraction Instance.documentFolderId,\n    recordType!AIA Extraction Instance.fieldCount,\n    recordType!AIA Extraction Instance.sections,\n    recordType!AIA Extraction Instance.boundingBoxes,\n    recordType!AIA Extraction Instance.responseDocumentId,\n    recordType!AIA Extraction Instance.sourceDocumentId\n  }\n)",
  "calls": [
    {
      "name": "AIA_Extraction_GetInstanceById",
      "type": "Expression Rule",
      "dep_type": "CALLS"
    }
  ],
  "called_by": []
}