{
  "uuid": "_a-0000e643-f7f1-8000-9bca-011c48011c48_1276927",
  "name": "AS_GCM_REF_ID_CLAUSE_SET_STATUS_FINALIZED",
  "type": "Constant",
  "description": "Contains Ref data Id for status Finalized\nValue: 40",
  "bundles": [
    "AS_GCM_Clause_Set_-",
    "AS_GCM_Clause_Set_-_3",
    "AS_GCM_Clause_Set_-_4",
    "AS_GCM_Clause_Set_-_5",
    "AS_GCM_Clause_Set_-_Copy_Clause_Set_Clauses",
    "AS_GCM_Clause_Set_-_6",
    "AS_GCM_Clause_Set",
    "AS_GCM_DRCA_Dynamic_Record_Context_Action_-_if_aisNullOrEmpty_property_rvrecordr",
    "AS_GCM_Clause_Set_Clause_Synced_-_Complete_Fill-ins",
    "AS_GCM_Write_Clause_Set_Related_Details",
    "AS_GCM_Write_to_ClauseText_Capture_Adt"
  ],
  "calls": [],
  "called_by": [
    {
      "name": "AS_GCM_CPS_readonlyClauseSetDetails",
      "type": "Interface",
      "dep_type": "USES_CONSTANT"
    },
    {
      "name": "AS_GCM_UT_clausesetSaveForAmendmentOrModification",
      "type": "Expression Rule",
      "dep_type": "USES_CONSTANT"
    },
    {
      "name": "AS_GCM_BL_GetPreviousSetIdForAmendmentOrModification",
      "type": "Expression Rule",
      "dep_type": "USES_CONSTANT"
    },
    {
      "name": "AS_GCM_BL_populateClauseSetClauseTextDetailsByBatching",
      "type": "Expression Rule",
      "dep_type": "USES_CONSTANT"
    },
    {
      "name": "AS_GCM_FM_finalizeClauseSet",
      "type": "Interface",
      "dep_type": "USES_CONSTANT"
    },
    {
      "name": "AS_GCM_varMapForCreateOrUpdateClauseSet",
      "type": "Expression Rule",
      "dep_type": "USES_CONSTANT"
    },
    {
      "name": "AS_GCM_FM_clauseSetValidation",
      "type": "Interface",
      "dep_type": "USES_CONSTANT"
    },
    {
      "name": "DEPRECATED_AS_GCM_BL_ClauseSetClausesVariableMap",
      "type": "Expression Rule",
      "dep_type": "USES_CONSTANT"
    },
    {
      "name": "AS GCM Finalize Clause Set",
      "type": "Process Model",
      "dep_type": "USES_CONSTANT"
    },
    {
      "name": "AS GCM View Document for Clause Set",
      "type": "Process Model",
      "dep_type": "USES_CONSTANT"
    },
    {
      "name": "AS GCM DRCA Dynamic Record Context Action",
      "type": "Record Type",
      "dep_type": "USES_CONSTANT"
    },
    {
      "name": "AS GCM Clause Set Clause Synced",
      "type": "Record Type",
      "dep_type": "USES_CONSTANT"
    }
  ]
}