{
  "uuid": "_a-0000e7f8-737a-8000-9bf7-011c48011c48_2513395",
  "name": "AS_GCM_CPS_contractDetailsInProvideClauseSetDetails",
  "type": "Interface",
  "description": "Contains Contract Details Fields",
  "bundles": [
    "AS_GCM_Clause_Set_-",
    "AS_GCM_Clause_Set_-_4",
    "AS_GCM_Clause_Set_-_Copy_Clause_Set_Clauses",
    "AS_GCM_DRCA_Dynamic_Record_Context_Action_-_if_aisNullOrEmpty_property_rvrecordr"
  ],
  "calls": [
    {
      "name": "AS_GCM_CRD_collapsibleSection",
      "type": "Interface",
      "dep_type": "CALLS"
    },
    {
      "name": "AS_GCM_DPL_CO_dropdownField",
      "type": "Interface",
      "dep_type": "CALLS"
    },
    {
      "name": "AS_GAM_translateMultipleBundleKeys",
      "type": "Expression Rule",
      "dep_type": "CALLS"
    },
    {
      "name": "AS_GCM_ENUM_CLAUSE_SET_SECTION_IDENTIFIER_CONTRACT_DETAILS",
      "type": "Constant",
      "dep_type": "USES_CONSTANT"
    },
    {
      "name": "AS_GCM_CO_UT_loadBundleFromFolder",
      "type": "Expression Rule",
      "dep_type": "CALLS"
    },
    {
      "name": "AS_GCM_dynamicFieldPropertiesForClauseSet",
      "type": "Expression Rule",
      "dep_type": "CALLS"
    },
    {
      "name": "AS_GCM_clauseSetContractDetailsDynamicComponentsMap",
      "type": "Expression Rule",
      "dep_type": "CALLS"
    },
    {
      "name": "AS_GCM_QE_getClauseSetDetails",
      "type": "Expression Rule",
      "dep_type": "CALLS"
    },
    {
      "name": "AS_CO_ENUM_QE_RETURN_TYPE_SINGLE_OBJECT",
      "type": "Constant",
      "dep_type": "USES_CONSTANT"
    }
  ],
  "called_by": [
    {
      "name": "AS_GCM_FM_createOrUpdateClauseSet",
      "type": "Interface",
      "dep_type": "CALLS"
    },
    {
      "name": "AS_GCM_FM_copyClauseSetClauses",
      "type": "Interface",
      "dep_type": "CALLS"
    }
  ]
}