{
  "uuid": "_a-0000ee39-4c1d-8000-9e29-011c48011c48_16493868",
  "name": "AS_GCM_CEDM_typeConfigMapForDataMigration_Question",
  "type": "Expression Rule",
  "description": "Config Maps for CEDM Export and Import process for Question",
  "bundles": [
    "AS_GCM_CEDM_Import_Environment_Data",
    "AS_GCM_CEDM_Write_Imported_Clause_Text_Data",
    "AS_GCM_CEDM_Export_Environment_Data",
    "AS_GCM_CEDM_Write_Imported_Data"
  ],
  "calls": [
    {
      "name": "AS_GCM_CO_INT_QUERY_RECORD_MAX_BATCH_SIZE",
      "type": "Constant",
      "dep_type": "USES_CONSTANT"
    },
    {
      "name": "AS GCM QNM T Question",
      "type": "Record Type",
      "dep_type": "USES_RECORD_TYPE"
    },
    {
      "name": "AS GCM QNM R Question",
      "type": "Record Type",
      "dep_type": "USES_RECORD_TYPE"
    },
    {
      "name": "AS GCM QNM R Response",
      "type": "Record Type",
      "dep_type": "USES_RECORD_TYPE"
    },
    {
      "name": "AS GCM QNM R Response Requirement",
      "type": "Record Type",
      "dep_type": "USES_RECORD_TYPE"
    }
  ],
  "called_by": [
    {
      "name": "AS_GCM_CEDM_typeConfigMapForDataMigration",
      "type": "Expression Rule",
      "dep_type": "CALLS"
    }
  ]
}