{
  "uuid": "_a-0000e5da-a251-8000-9bbe-011c48011c48_1021026",
  "name": "AS_GAM_UT_FormatUserForCreation",
  "type": "Expression Rule",
  "description": "Formats incoming data to see if creation, update or no action is needed for the user record",
  "bundles": [
    "AS_GAM_Add_User_to_User_Table"
  ],
  "calls": [
    {
      "name": "AS_CO_UT_isBlank",
      "type": "Expression Rule",
      "dep_type": "CALLS"
    },
    {
      "name": "AS_GAM_QE_getUser",
      "type": "Expression Rule",
      "dep_type": "CALLS"
    },
    {
      "name": "AS_CO_UT_checkIfUserExists",
      "type": "Expression Rule",
      "dep_type": "CALLS"
    },
    {
      "name": "AS_CO_UT_filterCdtByField",
      "type": "Expression Rule",
      "dep_type": "CALLS"
    },
    {
      "name": "AS_CO_UT_replaceNull",
      "type": "Expression Rule",
      "dep_type": "CALLS"
    },
    {
      "name": "AS_CO_UT_isNotBlank",
      "type": "Expression Rule",
      "dep_type": "CALLS"
    },
    {
      "name": "AS_CO_UT_updateCdtFields",
      "type": "Expression Rule",
      "dep_type": "CALLS"
    },
    {
      "name": "AS_CO_UT_cdtDistinctOnField",
      "type": "Expression Rule",
      "dep_type": "CALLS"
    },
    {
      "name": "AS_CO_UT_castToMapList",
      "type": "Expression Rule",
      "dep_type": "CALLS"
    },
    {
      "name": "AS_CO_ENUM_QE_RETURN_TYPE_OBJECT_ARRAY",
      "type": "Constant",
      "dep_type": "USES_CONSTANT"
    },
    {
      "name": "AS_GAM_APPREF_GSS_GETDATA_userEntity",
      "type": "Expression Rule",
      "dep_type": "CALLS"
    },
    {
      "name": "AS_GAM_APPREF_GSS_GETDATA_userType",
      "type": "Expression Rule",
      "dep_type": "CALLS"
    }
  ],
  "called_by": [
    {
      "name": "AS GAM Add User to User Table",
      "type": "Process Model",
      "dep_type": "CALLS"
    }
  ]
}