{
  "uuid": "_a-0000ebea-a421-8000-9cc1-011c48011c48_2326172",
  "name": "CMGT_LA_Message_RecordAction_Delete",
  "type": "Interface",
  "description": "Form interface for confirming the deletion of a message ",
  "bundles": [
    "CMGT_Comment_-_urnappiantranslation-stringv1bdfc41f5-5107-4d9d-8b18-bcbee4521c41"
  ],
  "calls": [
    {
      "name": "CMGT_UTIL_LoadBrandingMap",
      "type": "Expression Rule",
      "dep_type": "CALLS"
    },
    {
      "name": "CMGT_UTIL_DeleteConfirmation",
      "type": "Interface",
      "dep_type": "CALLS"
    },
    {
      "name": "Unknown",
      "type": "Translation String",
      "dep_type": "CALLS"
    },
    {
      "name": "Unknown",
      "type": "Translation String",
      "dep_type": "CALLS"
    },
    {
      "name": "Unknown",
      "type": "Translation String",
      "dep_type": "CALLS"
    },
    {
      "name": "Unknown",
      "type": "Translation String",
      "dep_type": "CALLS"
    },
    {
      "name": "Unknown",
      "type": "Translation String",
      "dep_type": "CALLS"
    },
    {
      "name": "CMGT_QR_GetComment",
      "type": "Expression Rule",
      "dep_type": "CALLS"
    }
  ],
  "called_by": [
    {
      "name": "CMGT_LA_Message_Delete",
      "type": "Process Model",
      "dep_type": "CALLS"
    }
  ]
}