{
  "uuid": "_a-0000ef2c-4192-8000-9e56-011c48011c48_353033",
  "name": "AIA_ClassificationInstance_CreateUpdateInstanceOutcomes",
  "type": "Expression Rule",
  "description": "Given a Classification Instance and a prompt response, returns a list of created or updated Classification Instance Outcome records to be written",
  "bundles": [
    "AIA_Classification_Save_Results"
  ],
  "calls": [
    {
      "name": "AIA_ExtractJson",
      "type": "Expression Rule",
      "dep_type": "CALLS"
    },
    {
      "name": "AIA_ClassificationInstanceOutcome_Initialize",
      "type": "Expression Rule",
      "dep_type": "CALLS"
    },
    {
      "name": "AIA_UTIL_SetRecordFields",
      "type": "Expression Rule",
      "dep_type": "CALLS"
    },
    {
      "name": "AIA_UTIL_Filter",
      "type": "Expression Rule",
      "dep_type": "CALLS"
    },
    {
      "name": "AIA_TXT_CLASSIFICATION_OUTCOME_OVERRIDE_DELETED",
      "type": "Constant",
      "dep_type": "USES_CONSTANT"
    },
    {
      "name": "AIA_TXT_CLASSIFICATION_OUTCOME_OVERRIDE_REMOVED",
      "type": "Constant",
      "dep_type": "USES_CONSTANT"
    }
  ],
  "called_by": [
    {
      "name": "AIA Classification Save Results",
      "type": "Process Model",
      "dep_type": "CALLS"
    }
  ]
}