{
  "uuid": "_a-0000e5da-a251-8000-9bbe-011c48011c48_1029541",
  "name": "AS_GSS_UT_getStatusDetailsByDueDate",
  "type": "Expression Rule",
  "description": "This rule is used to get the icon,color,label for Due Status by Due date",
  "sail_code": "if(\n  and(\n    today() > ri!dueDate,\n    rule!AS_CO_UT_isNotBlank(ri!dueDate)\n  ),\n  rule!AS_GSS_QE_getRefDataByTypes(\n    refDataIds: cons!AS_GSS_REF_ID_DATA_OVERDUE\n  ),\n  null\n)",
  "calls": [
    {
      "name": "AS_CO_UT_isNotBlank",
      "type": "Expression Rule",
      "dep_type": "CALLS"
    },
    {
      "name": "AS_GSS_QE_getRefDataByTypes",
      "type": "Expression Rule",
      "dep_type": "CALLS"
    },
    {
      "name": "AS_GSS_REF_ID_DATA_OVERDUE",
      "type": "Constant",
      "dep_type": "USES_CONSTANT"
    }
  ],
  "called_by": []
}