{
  "uuid": "0003ee1a-142b-8000-d5ac-7f0000014e7a",
  "name": "AS GSS View Vendor Decision",
  "type": "Process Model",
  "description": "The model with the interface to view vendor decision information",
  "bundles": [
    "AS_GSS_EvaluationVendor_SYNCEDRECORD_-_ruleAS_GSS_UT_returnDecisionLabelForViewA"
  ],
  "calls": [
    {
      "name": "AS_GSS_FM_vendorDecisionDetails",
      "type": "Interface",
      "dep_type": "CALLS"
    }
  ],
  "called_by": [
    {
      "name": "AS_GSS_EvaluationVendor_SYNCEDRECORD",
      "type": "Record Type",
      "dep_type": "CALLS"
    }
  ]
}