{
  "uuid": "_a-0000e5da-a251-8000-9bbe-011c48011c48_1036200",
  "name": "AS_GSS_CPS_vendorDetailsBoxSourceColumn",
  "type": "Interface",
  "description": "Column with where vendor data is found in the vendorDetailsBox",
  "bundles": [
    "AS_GSS_Ref_Vendor_SYNCEDRECORD_-_Add_Vendor",
    "AS_GSS_Vendor_RECORD_-_Add_Vendor"
  ],
  "calls": [
    {
      "name": "AS_GSS_CPS_vendorDetailsBoxFieldDisplay",
      "type": "Interface",
      "dep_type": "CALLS"
    },
    {
      "name": "AS_CO_UT_isBlank",
      "type": "Expression Rule",
      "dep_type": "CALLS"
    }
  ],
  "called_by": [
    {
      "name": "AS_GSS_CPS_vendorDetailsBox",
      "type": "Interface",
      "dep_type": "CALLS"
    }
  ]
}