{
  "uuid": "_a-0000e393-fbf1-8000-9ba2-011c48011c48_99402-tmg-am-am",
  "name": "AS_GSS_TMG_ENT_R_TASK_REF",
  "type": "Constant",
  "description": "Value: AS_GSS_TMG_R_TaskRef",
  "bundles": [],
  "calls": [],
  "called_by": [
    {
      "name": "AS_GSS_TMG_BTN_manageImportReferenceTasksGridButtons",
      "type": "Interface",
      "dep_type": "USES_CONSTANT"
    },
    {
      "name": "AS_GSS_TMG_CP_manageReferenceTask",
      "type": "Interface",
      "dep_type": "USES_CONSTANT"
    },
    {
      "name": "AS_GSS_TMG_QE_getTaskRefs",
      "type": "Expression Rule",
      "dep_type": "USES_CONSTANT"
    }
  ]
}