{
  "uuid": "_a-0000edc1-5343-8000-9e09-011c48011c48_15828653",
  "name": "AS_GSS_CPS_showRatingWithDescriptions",
  "type": "Interface",
  "description": "Interface to show rating and their descriptions for a rating type",
  "bundles": [
    "AS_GSS_ConsensusReport_SYNCEDRECORD_-_Open_Consensus_Form",
    "AS_GSS_ConsensusReport_SYNCEDRECORD_-_Continue_Consensus_Form"
  ],
  "calls": [
    {
      "name": "AS_GAM_CO_I18N_UT_displayLabel",
      "type": "Expression Rule",
      "dep_type": "CALLS"
    },
    {
      "name": "AS_GSS_BrandingValueByKey",
      "type": "Expression Rule",
      "dep_type": "CALLS"
    },
    {
      "name": "AS_GSS_Rating_SYNCEDRECORD",
      "type": "Record Type",
      "dep_type": "USES_RECORD_TYPE"
    }
  ],
  "called_by": [
    {
      "name": "AS_GSS_CPS_consensusClosingRemarks",
      "type": "Interface",
      "dep_type": "CALLS"
    }
  ]
}