{
  "uuid": "_a-0000e5da-a251-8000-9bbe-011c48011c48_965453",
  "name": "AS_GSS_QE_getEvaluationDocAdditionalInfo",
  "type": "Expression Rule",
  "description": "Returns evaluation docs with additional information from the view based on the given filter set",
  "bundles": [
    "AS_GSS_Evaluation_RECORD"
  ],
  "calls": [
    {
      "name": "AS_CO_UT_queryEntity",
      "type": "Expression Rule",
      "dep_type": "CALLS"
    },
    {
      "name": "AS_GSS_ENT_EVALUATION_DOC_ADDITIONAL_INFO",
      "type": "Constant",
      "dep_type": "USES_CONSTANT"
    },
    {
      "name": "AS_CO_ENUM_QE_RETURN_TYPE_DATA_SUBSET",
      "type": "Constant",
      "dep_type": "USES_CONSTANT"
    }
  ],
  "called_by": [
    {
      "name": "AS_GSS_GRD_evaluationDocsList",
      "type": "Interface",
      "dep_type": "CALLS"
    }
  ]
}