{
  "uuid": "_a-0000ece3-e0bc-8000-9dcb-011c48011c48_14348574",
  "name": "AS_GSS_TMG_QR_getTaskRef",
  "type": "Expression Rule",
  "description": "Generic query expression for Tasks Ref record data",
  "bundles": [],
  "calls": [
    {
      "name": "AS_CO_UT_queryRecord",
      "type": "Expression Rule",
      "dep_type": "CALLS"
    },
    {
      "name": "AS_GSS_TMG_Task_Ref_SYNCEDRECORD",
      "type": "Record Type",
      "dep_type": "USES_RECORD_TYPE"
    },
    {
      "name": "AS_CO_ENUM_QE_RETURN_TYPE_SINGLE_OBJECT",
      "type": "Constant",
      "dep_type": "USES_CONSTANT"
    }
  ],
  "called_by": []
}