{
  "uuid": "_a-0000ea4b-69d2-8000-9c9e-011c48011c48_7149661",
  "name": "AS_GSS_QE_getEvaluationResponsesWithSelection",
  "type": "Expression Rule",
  "description": "Query entity to get evaluation responses with selection",
  "bundles": [],
  "calls": [
    {
      "name": "AS_GAM_UT_queryEntityWithSelection",
      "type": "Expression Rule",
      "dep_type": "CALLS"
    },
    {
      "name": "AS_CO_UT_isNotBlank",
      "type": "Expression Rule",
      "dep_type": "CALLS"
    },
    {
      "name": "AS_GSS_ENT_EVALUATION_RESPONSES",
      "type": "Constant",
      "dep_type": "USES_CONSTANT"
    },
    {
      "name": "AS_CO_ENUM_QE_RETURN_TYPE_DATA_SUBSET",
      "type": "Constant",
      "dep_type": "USES_CONSTANT"
    }
  ],
  "called_by": []
}